digitize/__init__.py
digitize/attrstr.py
digitize/bulk.py
digitize/cli.py
digitize/config.py
digitize/consts.py
digitize/md.py
digitize/patterns.py
digitize/run.py
digitize/sentinel.py
digitize/stages.py
digitize/units.py
digitize/tasks/__init__.py
digitize/tasks/fractions.py
digitize/tasks/itd.py
digitize/tasks/ordinal.py
digitize/tasks/replace_multipliers.py
digitize/tasks/roman.py
digitize/tasks/simple_eval.py
digitize/tasks/unit_cascade.py
digitize/test_cases/__init__.py
digitize/test_cases/decimal.py
digitize/test_cases/edge.py
digitize/test_cases/examples.py
digitize/test_cases/formatting.py
digitize/test_cases/math.py
digitize/test_cases/more.py
digitize/test_cases/ordinal_time.py
digitize/test_cases/roman.py
digitize/test_cases/sci.py
digitize/test_cases/signed.py
digitize/test_cases/stories.py
digitize/test_cases/suffix.py
digitize/test_cases/ths.py
modularizer_digitize-0.2.0.dist-info/METADATA
modularizer_digitize-0.2.0.dist-info/WHEEL
modularizer_digitize-0.2.0.dist-info/entry_points.txt
modularizer_digitize-0.2.0.dist-info/top_level.txt
modularizer_digitize-0.2.0.dist-info/RECORD
