Metadata-Version: 2.4
Name: modularizer-digitize
Version: 0.2.0
Summary: A natural language numerical string preprocessor
Author-email: Torin Halsted <modularizer@gmail.com>
License: Unlicense
Project-URL: Homepage, https://github.com/modularizer/digitize
Project-URL: Repository, https://github.com/modularizer/digitize
Project-URL: Issues, https://github.com/modularizer/digitize/issues
Requires-Python: >=3.10
Provides-Extra: test
